.gitignore
.travis.yml
CONTRIBUTING.md
CONTRIBUTORS.md
LICENSE
MANIFEST.in
README.md
requirements.txt
setup.py
.github/ISSUE_TEMPLATE.md
.github/PULL_REQUEST_TEMPLATE.md
docs/Makefile
docs/source/argparse_utils.rst
docs/source/conf.py
docs/source/emg.rst
docs/source/emg_norm.rst
docs/source/emg_select.rst
docs/source/emg_split.rst
docs/source/index.rst
docs/source/inputs-outputs.rst
docs/source/installation.rst
docs/source/overview.rst
docs/source/quickstart.rst
emg_analyzer/__init__.py
emg_analyzer/argparse_utils.py
emg_analyzer/emg.py
emg_analyzer/utils.py
emg_analyzer.egg-info/PKG-INFO
emg_analyzer.egg-info/SOURCES.txt
emg_analyzer.egg-info/dependency_links.txt
emg_analyzer.egg-info/entry_points.txt
emg_analyzer.egg-info/not-zip-safe
emg_analyzer.egg-info/requires.txt
emg_analyzer.egg-info/top_level.txt
emg_analyzer/scripts/__init__.py
emg_analyzer/scripts/emg_group_tracks.py
emg_analyzer/scripts/emg_norm.py