Metadata-Version: 1.2
Name: emg-analyzer
Version: 0.1
Summary: parse emg recording and normalize the voltage
Home-page: UNKNOWN
Author: Bertrand Neron
Author-email: freeh4cker@gmail.com
License: BSD3
Keywords: EMG,data science,data normalization
Platform: Unix
Platform: Linux
Platform: MacOsX
Classifier: Development Status :: 4 - Beta
Classifier: Intended Audience :: Developers 
Classifier: Intended Audience :: Science/Research
Classifier: License :: OSI Approved :: BSD License
Classifier: Operating System :: OS Independent
Classifier: Programming Language :: Python :: 3
Classifier: Programming Language :: Python :: 3.6
Classifier: Environment :: Console
Classifier: Topic :: Scientific/Engineering :: Information Analysis
Requires-Python: >=3.6
